setup.py
PythonWebDav/AudioFiler.py
PythonWebDav/Filer.py
PythonWebDav/Handler.py
PythonWebDav/Server.py
PythonWebDav/VirtualFS.py
PythonWebDav/WebDavServer.py
PythonWebDav/XmlWorker.py
PythonWebDav/__init__.py
PythonWebDav/__main__.py
SimpleWebDav.egg-info/PKG-INFO
SimpleWebDav.egg-info/SOURCES.txt
SimpleWebDav.egg-info/dependency_links.txt
SimpleWebDav.egg-info/requires.txt
SimpleWebDav.egg-info/top_level.txt