Metadata-Version: 1.0
Name: SimpleWebDav
Version: 0.1
Summary: Simple WebDav library
Home-page: UNKNOWN
Author: Kosmachev Alex
Author-email: adkosmachev@edu.hse.ru
License: UNKNOWN
Platform: UNKNOWN
